{
  "type": "FeatureCollection",
  "features": [
    {
      "type": "Feature",
      "geometry": {
        "type": "Point",
        "coordinates": [
          2.2622912,
          48.8234676
        ]
      },
      "properties": {
        "osm_type": "W",
        "osm_id": 806436030,
        "osm_key": "highway",
        "osm_value": "secondary",
        "type": "street",
        "postcode": "92130",
        "countrycode": "FR",
        "name": "Boulevard Garibaldi",
        "district": "Quartier Bords et Val de Seine / Les Arches",
        "city": "Issy-les-Moulineaux",
        "county": "Hauts-de-Seine",
        "state": "Île-de-France",
        "country": "France",
        "extent": [
          2.2621588,
          48.8239349,
          2.2623222,
          48.8230146
        ]
      },
      "id": "sndF8"
    }
  ]
}